{
  "run_name": "cuda-mainline",
  "preset": "balanced",
  "engine_path": "C:\\Users\\coope\\Test Code\\chess-ancient\\chess-resurected\\engine\\target\\release\\chess-resurected.exe",
  "stockfish_path": "C:\\Users\\coope\\AppData\\Local\\Microsoft\\WinGet\\Packages\\Stockfish.Stockfish_Microsoft.Winget.Source_8wekyb3d8bbwe\\stockfish\\stockfish.EXE",
  "device": "cuda",
  "amp": true,
  "seed": 1,
  "pipeline_mode": "finite",
  "games": 1000,
  "cycle_games": 100,
  "max_cycles": 1,
  "warmup_cycles": 1,
  "max_ply": 140,
  "selfplay_mode": "mcts",
  "selfplay_movetime_ms": 30,
  "mcts_simulations": 64,
  "interactive_simulations": 64,
  "random_opening_moves": 4,
  "temperature": 1.1,
  "temp_threshold": 24,
  "c_puct": 1.0,
  "draw_rate_warning": 0.75,
  "decisive_sample_weight": 2,
  "replay_buffer_size": 100000,
  "train_epochs": 2,
  "batch_size": 512,
  "learning_rate": 0.001,
  "weight_decay": 0.0001,
  "num_blocks": 6,
  "channels": 128,
  "dropout_p": 0.1,
  "run_ladder": true,
  "ladder_games": 20,
  "ladder_movetime_ms": 100,
  "opponent_elo": 2300,
  "fm_target": 2300
}